[
    {
        "sn": "47",
        "name": "Magic Bus Box",
        "price": 210,
        "img": "https://i.ibb.co/Yb7w0JV/71-Nog-3d-BJL.jpg"
    },
    {
        "sn": "48",
        "name": "Geometry Box",
        "price": 90,
        "img": "https://i.ibb.co/rHMpx6s/9ea2042c05d8d251f325a314d5b69dc1.jpg"
    },
    {
        "sn": "49",
        "name": "Water Colour Pen",
        "price": 100,
        "img": "https://i.ibb.co/hCg3CJ3/21d1cac158bf4c2490e7db76d88a6286.jpg"
    },
    {
        "sn": "50",
        "name": "Matador i-teen pen",
        "price": 10,
        "img": "https://i.ibb.co/tQwqqqD/619f6b5b52ee8.png"
    },
    {
        "sn": "51",
        "name": "Compass",
        "price": 50,
        "img": "https://i.ibb.co/0c0bGQY/2855a758d91d41e483182ac7db7916fd.jpg"
    },
    {
        "sn": "51",
        "name": "Khata 124 pages",
        "price": 80,
        "img": "https://i.ibb.co/7NKfd2H/2022-06-14-62a8599e2ffe5.png"
    },
    {
        "sn": "53",
        "name": "MATADOR HI-SCHOOL",
        "price": 5,
        "img": "https://i.ibb.co/4f091yd/63528c7b95dc1527cc010443-matador-hi-school-ballpen-fine-point.jpg"
    },
    {
        "sn": "54",
        "name": "Eraser",
        "price": 10,
        "img": "https://i.ibb.co/tC1Sq9D/1666092470-Cw-Y9i.jpg"
    },
    {
        "sn": "55",
        "name": "Sharpner",
        "price": 20,
        "img": "https://i.ibb.co/kG3MXqY/1666084436-Xek-Yy.jpg"
    },
    {
        "sn": "56",
        "name": "Khata 200 pages",
        "price": 150,
        "img": "https://i.ibb.co/ZWfLQMg/AjQkn.jpg"
    },
    {
        "sn": "57",
        "name": "Graph Paper",
        "price": 2,
        "img": "https://i.ibb.co/nRKc7hq/e4328241f42dd299c2c62029c7e4db57.jpg"
    },
    {
        "sn": "58",
        "name": "Scale",
        "price": 20,
        "img": "https://i.ibb.co/GTFJkj4/7f9a336726751772c7e7ac2cdcc8379a.jpg"
    },
    {
        "sn": "59",
        "name": "Colouring Box",
        "price": 430,
        "img": "https://i.ibb.co/rK9d1Qd/colour.jpg"
    },
    {
        "sn": "60",
        "name": "Stapler",
        "price": 50,
        "img": "https://i.ibb.co/mb056bb/Stepler.jpg"
    },
    {
        "sn": "61",
        "name": "Stapler Pin",
        "price": 20,
        "img": "https://i.ibb.co/cCH5DyV/kangaro-stapler-pin-no10-small-1000-staples.jpg"
    }
]